Metadata-Version: 2.1
Name: heuristic-binning-entropy
Version: 0.2.1
Summary: entropy heuristic binning
Home-page: https://github.com/shazri/entropyheuristicbinning
Author: shazri_shahrir
Author-email: mdshazrishahrir@gmail.com
License: UNKNOWN
Platform: UNKNOWN
Classifier: Programming Language :: Python :: 3
Classifier: License :: OSI Approved :: MIT License
Classifier: Operating System :: OS Independent
Requires-Python: >=3.0
License-File: LICENSE
